api.py
claimer.py
configuration.py
downloader.py
packtPublishingFreeEbook.py
utils/__init__.py
utils/anticaptcha.py
utils/google_drive.py
utils/logger.py
utils/mail.py
packt-1.4.0.dist-info/LICENSE
packt-1.4.0.dist-info/METADATA
packt-1.4.0.dist-info/WHEEL
packt-1.4.0.dist-info/entry_points.txt
packt-1.4.0.dist-info/top_level.txt
packt-1.4.0.dist-info/RECORD
