Metadata-Version: 2.1
Name: packt
Version: 1.4.0
Summary: Script for grabbing daily Packt Free Learning ebooks
Home-page: https://github.com/luk6xff/Packt-Publishing-Free-Learning
Author: Łukasz Uszko
Author-email: lukasz.uszko@gmail.com
License: MIT
Download-URL: https://github.com/luk6xff/Packt-Publishing-Free-Learning/archive/v1.4.0.tar.gz
Platform: UNKNOWN
Classifier: Programming Language :: Python :: 3.5
Classifier: Programming Language :: Python :: 3.6
Classifier: Programming Language :: Python :: 3.7
Requires-Dist: click (==7.0)
Requires-Dist: google-api-python-client (==1.6.3)
Requires-Dist: requests (==2.20.0)
Requires-Dist: python-slugify (==1.2.6)
Provides-Extra: dev
Requires-Dist: mccabe (==0.6.1) ; extra == 'dev'
Requires-Dist: pycodestyle (==2.4.0) ; extra == 'dev'
Requires-Dist: pyflakes (==2.0.0) ; extra == 'dev'
Requires-Dist: pylama (==7.6.5) ; extra == 'dev'
